Workbook

Sheet Resumen Ejecutivo
B2: PULSO: ANÁLISIS ECONÓMICO DEL SERVICIO SaaS
B3: Cartera Starter + Pro Gym · costo económico y efectivo separados · beneficio MYPE condicionado
C4: GIMNASIOS AL CIERRE | F4: INGRESOS TOTALES AÑO 1 | I4: EQUILIBRIO OPERATIVO | L4: LIQUIDEZ INICIAL MÍNIMA
C5: ='Clientes e Ingresos'!F17 -> 14 | F5: ='Clientes e Ingresos'!H18 -> 2780000 | I5: ='Punto de Equilibrio'!D13 -> 6 | L5: ='Estados Financieros'!C9 -> 40000
B8: RESUMEN DEL PROYECTO
B9: ="Pulso: escenario de 1 Starter y el resto Pro Gym; "&'Clientes e Ingresos'!F17&" activos al cierre. No son ventas confirmadas."&CHAR(10)&"• Viáticos: ₡40 000 mes 1; ₡12 000/mes después. Diez prospectos, meta cinco altas iniciales."&CHAR(10)&"• Hora técnica: salario MTSS ₡496 838,17 ÷30÷8. Trabajo propio aportado sin pago."&CHAR(10)&"• Desarrollo: ₡"&TEXT('Egresos e Inversión'!D12,"#,##0.00")&" de costo económico; no desembolso inicial."&CHAR(10)&"• Resultado económico anual: ₡"&TEXT('Estados Financieros'!C30,"#,##0.00")&". Renta 0 condicionada a formalización MYPE."&CHAR(10)&"• Precios de venta conservados. Equilibrio mensual distinto de recuperar el trabajo invertido." -> Pulso: escenario de 1 Starter y el resto Pro Gym; 14 activos al cierre. No son ventas confirmadas. • Viáticos: ₡40 000 mes 1; ₡12 000/mes después. Diez prospectos, meta cinco altas iniciales. • Hora técnica: salario MTSS ₡496 838,17 ÷30÷8. Trabajo propio aportado sin pago. • Desarrollo: ₡198735,268.00 de costo económico; no desembolso inicial. • Resultado económico anual: ₡596044,357.25. Renta 0 condicionada a formalización MYPE. • Precios de venta conservados. Equilibrio mensual distinto de recuperar el trabajo invertido.

Sheet Clientes e Ingresos
B2: PROYECCIÓN DE CLIENTES E INGRESOS (MRR)
B3: Escenario: 1 Starter y el resto Pro Gym; mensualidad completa desde el alta. Sin ventas Premium/Enterprise.
B5: Mes | C5: Gimnasios Iniciales | D5: Nuevos Clientes | E5: Cancelaciones (unidades) | F5: Gimnasios Activos Final | G5: Precio medio ponderado (₡) | H5: Ingreso Mensual MRR (₡) | I5: Ingreso Acumulado (₡)
B6: Mes 1 | C6: 0 | D6: 5 | E6: 0 | F6: =C6+D6-E6 -> 5 | G6: =IF(F6>0,(15000+MAX(0,F6-1)*25000)/F6,0) -> 23000 | H6: =ROUND(F6*G6,2) -> 115000 | I6: =SUM($H$6:H6) -> 115000
B7: Mes 2 | C7: =F6 -> 5 | D7: 1 | E7: 0 | F7: =C7+D7-E7 -> 6 | G7: =IF(F7>0,(15000+MAX(0,F7-1)*25000)/F7,0) -> 23333.333 | H7: =ROUND(F7*G7,2) -> 140000 | I7: =SUM($H$6:H7) -> 255000
B8: Mes 3 | C8: =F7 -> 6 | D8: 1 | E8: 0 | F8: =C8+D8-E8 -> 7 | G8: =IF(F8>0,(15000+MAX(0,F8-1)*25000)/F8,0) -> 23571.429 | H8: =ROUND(F8*G8,2) -> 165000 | I8: =SUM($H$6:H8) -> 420000
B9: Mes 4 | C9: =F8 -> 7 | D9: 1 | E9: 0 | F9: =C9+D9-E9 -> 8 | G9: =IF(F9>0,(15000+MAX(0,F9-1)*25000)/F9,0) -> 23750 | H9: =ROUND(F9*G9,2) -> 190000 | I9: =SUM($H$6:H9) -> 610000
B10: Mes 5 | C10: =F9 -> 8 | D10: 1 | E10: 0 | F10: =C10+D10-E10 -> 9 | G10: =IF(F10>0,(15000+MAX(0,F10-1)*25000)/F10,0) -> 23888.889 | H10: =ROUND(F10*G10,2) -> 215000 | I10: =SUM($H$6:H10) -> 825000
B11: Mes 6 | C11: =F10 -> 9 | D11: 1 | E11: 1 | F11: =C11+D11-E11 -> 9 | G11: =IF(F11>0,(15000+MAX(0,F11-1)*25000)/F11,0) -> 23888.889 | H11: =ROUND(F11*G11,2) -> 215000 | I11: =SUM($H$6:H11) -> 1040000
B12: Mes 7 | C12: =F11 -> 9 | D12: 1 | E12: 0 | F12: =C12+D12-E12 -> 10 | G12: =IF(F12>0,(15000+MAX(0,F12-1)*25000)/F12,0) -> 24000 | H12: =ROUND(F12*G12,2) -> 240000 | I12: =SUM($H$6:H12) -> 1280000
B13: Mes 8 | C13: =F12 -> 10 | D13: 1 | E13: 0 | F13: =C13+D13-E13 -> 11 | G13: =IF(F13>0,(15000+MAX(0,F13-1)*25000)/F13,0) -> 24090.909 | H13: =ROUND(F13*G13,2) -> 265000 | I13: =SUM($H$6:H13) -> 1545000
B14: Mes 9 | C14: =F13 -> 11 | D14: 1 | E14: 0 | F14: =C14+D14-E14 -> 12 | G14: =IF(F14>0,(15000+MAX(0,F14-1)*25000)/F14,0) -> 24166.667 | H14: =ROUND(F14*G14,2) -> 290000 | I14: =SUM($H$6:H14) -> 1835000
B15: Mes 10 | C15: =F14 -> 12 | D15: 1 | E15: 1 | F15: =C15+D15-E15 -> 12 | G15: =IF(F15>0,(15000+MAX(0,F15-1)*25000)/F15,0) -> 24166.667 | H15: =ROUND(F15*G15,2) -> 290000 | I15: =SUM($H$6:H15) -> 2125000
B16: Mes 11 | C16: =F15 -> 12 | D16: 1 | E16: 0 | F16: =C16+D16-E16 -> 13 | G16: =IF(F16>0,(15000+MAX(0,F16-1)*25000)/F16,0) -> 24230.769 | H16: =ROUND(F16*G16,2) -> 315000 | I16: =SUM($H$6:H16) -> 2440000
B17: Mes 12 | C17: =F16 -> 13 | D17: 1 | E17: 0 | F17: =C17+D17-E17 -> 14 | G17: =IF(F17>0,(15000+MAX(0,F17-1)*25000)/F17,0) -> 24285.714 | H17: =ROUND(F17*G17,2) -> 340000 | I17: =SUM($H$6:H17) -> 2780000
B18: TOTAL AÑO 1 | C18: =C6 -> 0 | D18: =SUM(D6:D17) -> 16 | E18: =SUM(E6:E17) -> 2 | F18: =F17 -> 14 | G18: =IFERROR(H18/SUM(F6:F17),0) -> 23965.517 | H18: =SUM(H6:H17) -> 2780000 | I18: =I17 -> 2780000

Sheet Egresos e Inversión
B2: PRESUPUESTO DE EGRESOS E INVERSIÓN INICIAL
B3: Costos económicos: trabajo propio valorado con MTSS 2026; aportado sin pago. Viáticos iniciales y recurrentes diferenciados.
B5: 1. DESARROLLO INICIAL (UNA SOLA VEZ)
B6: Rubro / Concepto | C6: Descripción | D6: Monto Estimado (₡)
B7: Aislamiento de gimnasios | C7: Permisos y separación multiempresa: 24 h | D7: =24*(496838.17/30/8) -> 49683.817
B8: Autenticación dedicada | C8: Ruteo de usuarios a bases dedicadas: 24 h | D8: =24*(496838.17/30/8) -> 49683.817
B9: Personalización y cupos | C9: Marca/subdominios 12 h + límites de archivos e IA 8 h | D9: =20*(496838.17/30/8) -> 41403.181
B10: Mensajería y tareas | C10: SES, Redis y worker: 12 h | D10: =12*(496838.17/30/8) -> 24841.909
B11: Pruebas y entrega | C11: Aislamiento, carga y documentación: 16 h | D11: =16*(496838.17/30/8) -> 33122.545
B12: TOTAL DESARROLLO INICIAL | D12: =SUM(D7:D11) -> 198735.27
B15: 2. GASTOS OPERATIVOS FIJOS MENSUALES
B16: Rubro de Gasto Fijo | C16: Detalle Operativo | D16: Monto Mensual Base (₡)
B17: Infraestructura y dominio | C17: Vercel + Supabase + API + dominio + Redis + worker + workspace | D17: =20*500+25*500+10*500+15/12*500+10*500+25*500+25*500 -> 58125
B18: Transporte y viáticos | C18: Mes 1 ₡40 000; después ₡12 000/mes | D18: =2*2*2000+4000 -> 12000
B19: Publicidad digital | C19: Anuncios para validación comercial | D19: =5000 -> 5000
B20: Correo y diseño | C20: Workspace: US$7; diseño: US$5; cambio ₡500/USD | D20: =(7+5)*500 -> 6000
B21: Mantenimiento y captación | C21: 4 h mantenimiento + 12 h comerciales/mes | D21: =(4+2*3*2)*(496838.17/30/8) -> 33122.545 | E21: Mes 1: 36 h comerciales; meses 2–12: 12 h. Aporte del equipo sin pago, no deuda.
B22: TOTAL GASTOS FIJOS BASE / MES | D22: =SUM(D17:D21) -> 114247.54
B25: 3. VARIABLE UNITARIO: MEZCLA INICIAL
B26: Componente Variable | C26: Descripción / Proveedor | D26: Costo por Gym / Mes (₡)
B27: Soporte mensual | C27: 0,5 h × referencia MTSS por hora | D27: =0.5*(496838.17/30/8) -> 1035.0795
B28: Correo e IA | C28: SES + GPT-4.1 mini; ponderado por miembros de la mezcla | D28: =(ROUND((((80*2+20)*0.16/1000+(80*2+20)*32/1000000*0.12)*500),2)+80*2*(4000*0.4+300*1.6)/1000000*500+MAX(0,'Clientes e Ingresos'!F6-1)*(ROUND((((200*2+20)*0.16/1000+(200*2+20)*32/1000000*0.12)*500),2)+200*2*(4000*0.4+300*1.6)/1000000*500))/'Clientes e Ingresos'!F6 -> 396.558
B29: Comisiones | C29: Transferencia sin pasarela contratada | D29: =0 -> 0
B30: COSTO VARIABLE TOTAL POR GIMNASIO | D30: =SUM(D27:D29) -> 1431.6375 | E30: Base por gimnasio en mes 1; nube excedente e instalaciones se calculan aparte según cartera y altas.
B33: 4. PROYECCIÓN MENSUAL DE EGRESOS (AÑO 1)
B34: Mes | C34: Gimnasios Activos | D34: Gastos Fijos (OPEX) | E34: Variables + altas + nube | F34: Egresos sin desarrollo
B35: Mes 1 | C35: ='Clientes e Ingresos'!F6 -> 5 | D35: =$D$22+(3*2*2000+2*4000+8000+2*2*3000-$D$18)+(6*3*2-2*3*2)*(496838.17/30/8) -> 191931.36 | E35: =C35*$D$27+(ROUND((((80*2+20)*0.16/1000+(80*2+20)*32/1000000*0.12)*500),2)+80*2*(4000*0.4+300*1.6)/1000000*500+MAX(0,C35-1)*(ROUND((((200*2+20)*0.16/1000+(200*2+20)*32/1000000*0.12)*500),2)+200*2*(4000*0.4+300*1.6)/1000000*500))+C35*$D$29+'Clientes e Ingresos'!D6*(8*(496838.17/30/8))+(ROUND((MAX(0,((1)*1+(MAX(0,C35-1))*3+(0)*8+(0)*16)-100)*0.0213+MAX(0,((1)*1.056+(MAX(0,C35-1))*2.63999999999999+(0)*6.6+(0)*13.2)-250)*0.09+(MAX(0,ROUNDUP((((1)*0.06+(MAX(0,C35-1))*0.15)+((0)*0.375+(0)*0.75)*0.05)*2,0)-8)+((1)*0+(MAX(0,C35-1))*0+(0)*0+(0)*0))*0.125+IF(((1)*80+(MAX(0,C35-1))*200)<=2000,10,IF(((1)*80+(MAX(0,C35-1))*200)<=5000,15,IF(((1)*80+(MAX(0,C35-1))*200)<=10000,60,110)))-10)*500,2)+ROUND((MAX(0,((1)*0.166864+(MAX(0,C35-1))*0.41716+(0)*1.0429+(0)*2.0858)+20*2*2*0.0035+30*(1/3600*0.128+5/3600*0.0106)-20)+IF(AND(((1)*55680+(MAX(0,C35-1))*139200+(0)*348000+(0)*696000)<=1000000,((1)*1.536+(MAX(0,C35-1))*3.84+(0)*9.6+(0)*19.2)<=1000),0,IF(((1)*55680+(MAX(0,C35-1))*139200+(0)*348000+(0)*696000)<=10000000,20,IF(((1)*55680+(MAX(0,C35-1))*139200+(0)*348000+(0)*696000)<=50000000,100,300)))+MAX(0,ROUNDUP(((1)*80+(MAX(0,C35-1))*200+(0)*500+(0)*1000)/5000,0)-1)*25+IF(((1)*80+(MAX(0,C35-1))*200+(0)*500+(0)*1000)>5000,32-10,0))*500,2)) -> 89964.549 | F35: =D35+E35 -> 281895.91
B36: Mes 2 | C36: ='Clientes e Ingresos'!F7 -> 6 | D36: =$D$22 -> 114247.54 | E36: =C36*$D$27+(ROUND((((80*2+20)*0.16/1000+(80*2+20)*32/1000000*0.12)*500),2)+80*2*(4000*0.4+300*1.6)/1000000*500+MAX(0,C36-1)*(ROUND((((200*2+20)*0.16/1000+(200*2+20)*32/1000000*0.12)*500),2)+200*2*(4000*0.4+300*1.6)/1000000*500))+C36*$D$29+'Clientes e Ingresos'!D7*(8*(496838.17/30/8))+(ROUND((MAX(0,((1)*1+(MAX(0,C36-1))*3+(0)*8+(0)*16)-100)*0.0213+MAX(0,((1)*1.056+(MAX(0,C36-1))*2.63999999999999+(0)*6.6+(0)*13.2)-250)*0.09+(MAX(0,ROUNDUP((((1)*0.06+(MAX(0,C36-1))*0.15)+((0)*0.375+(0)*0.75)*0.05)*2,0)-8)+((1)*0+(MAX(0,C36-1))*0+(0)*0+(0)*0))*0.125+IF(((1)*80+(MAX(0,C36-1))*200)<=2000,10,IF(((1)*80+(MAX(0,C36-1))*200)<=5000,15,IF(((1)*80+(MAX(0,C36-1))*200)<=10000,60,110)))-10)*500,2)+ROUND((MAX(0,((1)*0.166864+(MAX(0,C36-1))*0.41716+(0)*1.0429+(0)*2.0858)+20*2*2*0.0035+30*(1/3600*0.128+5/3600*0.0106)-20)+IF(AND(((1)*55680+(MAX(0,C36-1))*139200+(0)*348000+(0)*696000)<=1000000,((1)*1.536+(MAX(0,C36-1))*3.84+(0)*9.6+(0)*19.2)<=1000),0,IF(((1)*55680+(MAX(0,C36-1))*139200+(0)*348000+(0)*696000)<=10000000,20,IF(((1)*55680+(MAX(0,C36-1))*139200+(0)*348000+(0)*696000)<=50000000,100,300)))+MAX(0,ROUNDUP(((1)*80+(MAX(0,C36-1))*200+(0)*500+(0)*1000)/5000,0)-1)*25+IF(((1)*80+(MAX(0,C36-1))*200+(0)*500+(0)*1000)>5000,32-10,0))*500,2)) -> 25204.949 | F36: =D36+E36 -> 139452.49
B37: Mes 3 | C37: ='Clientes e Ingresos'!F8 -> 7 | D37: =$D$22 -> 114247.54 | E37: =C37*$D$27+(ROUND((((80*2+20)*0.16/1000+(80*2+20)*32/1000000*0.12)*500),2)+80*2*(4000*0.4+300*1.6)/1000000*500+MAX(0,C37-1)*(ROUND((((200*2+20)*0.16/1000+(200*2+20)*32/1000000*0.12)*500),2)+200*2*(4000*0.4+300*1.6)/1000000*500))+C37*$D$29+'Clientes e Ingresos'!D8*(8*(496838.17/30/8))+(ROUND((MAX(0,((1)*1+(MAX(0,C37-1))*3+(0)*8+(0)*16)-100)*0.0213+MAX(0,((1)*1.056+(MAX(0,C37-1))*2.63999999999999+(0)*6.6+(0)*13.2)-250)*0.09+(MAX(0,ROUNDUP((((1)*0.06+(MAX(0,C37-1))*0.15)+((0)*0.375+(0)*0.75)*0.05)*2,0)-8)+((1)*0+(MAX(0,C37-1))*0+(0)*0+(0)*0))*0.125+IF(((1)*80+(MAX(0,C37-1))*200)<=2000,10,IF(((1)*80+(MAX(0,C37-1))*200)<=5000,15,IF(((1)*80+(MAX(0,C37-1))*200)<=10000,60,110)))-10)*500,2)+ROUND((MAX(0,((1)*0.166864+(MAX(0,C37-1))*0.41716+(0)*1.0429+(0)*2.0858)+20*2*2*0.0035+30*(1/3600*0.128+5/3600*0.0106)-20)+IF(AND(((1)*55680+(MAX(0,C37-1))*139200+(0)*348000+(0)*696000)<=1000000,((1)*1.536+(MAX(0,C37-1))*3.84+(0)*9.6+(0)*19.2)<=1000),0,IF(((1)*55680+(MAX(0,C37-1))*139200+(0)*348000+(0)*696000)<=10000000,20,IF(((1)*55680+(MAX(0,C37-1))*139200+(0)*348000+(0)*696000)<=50000000,100,300)))+MAX(0,ROUNDUP(((1)*80+(MAX(0,C37-1))*200+(0)*500+(0)*1000)/5000,0)-1)*25+IF(((1)*80+(MAX(0,C37-1))*200+(0)*500+(0)*1000)>5000,32-10,0))*500,2)) -> 26690.439 | F37: =D37+E37 -> 140937.98
B38: Mes 4 | C38: ='Clientes e Ingresos'!F9 -> 8 | D38: =$D$22 -> 114247.54 | E38: =C38*$D$27+(ROUND((((80*2+20)*0.16/1000+(80*2+20)*32/1000000*0.12)*500),2)+80*2*(4000*0.4+300*1.6)/1000000*500+MAX(0,C38-1)*(ROUND((((200*2+20)*0.16/1000+(200*2+20)*32/1000000*0.12)*500),2)+200*2*(4000*0.4+300*1.6)/1000000*500))+C38*$D$29+'Clientes e Ingresos'!D9*(8*(496838.17/30/8))+(ROUND((MAX(0,((1)*1+(MAX(0,C38-1))*3+(0)*8+(0)*16)-100)*0.0213+MAX(0,((1)*1.056+(MAX(0,C38-1))*2.63999999999999+(0)*6.6+(0)*13.2)-250)*0.09+(MAX(0,ROUNDUP((((1)*0.06+(MAX(0,C38-1))*0.15)+((0)*0.375+(0)*0.75)*0.05)*2,0)-8)+((1)*0+(MAX(0,C38-1))*0+(0)*0+(0)*0))*0.125+IF(((1)*80+(MAX(0,C38-1))*200)<=2000,10,IF(((1)*80+(MAX(0,C38-1))*200)<=5000,15,IF(((1)*80+(MAX(0,C38-1))*200)<=10000,60,110)))-10)*500,2)+ROUND((MAX(0,((1)*0.166864+(MAX(0,C38-1))*0.41716+(0)*1.0429+(0)*2.0858)+20*2*2*0.0035+30*(1/3600*0.128+5/3600*0.0106)-20)+IF(AND(((1)*55680+(MAX(0,C38-1))*139200+(0)*348000+(0)*696000)<=1000000,((1)*1.536+(MAX(0,C38-1))*3.84+(0)*9.6+(0)*19.2)<=1000),0,IF(((1)*55680+(MAX(0,C38-1))*139200+(0)*348000+(0)*696000)<=10000000,20,IF(((1)*55680+(MAX(0,C38-1))*139200+(0)*348000+(0)*696000)<=50000000,100,300)))+MAX(0,ROUNDUP(((1)*80+(MAX(0,C38-1))*200+(0)*500+(0)*1000)/5000,0)-1)*25+IF(((1)*80+(MAX(0,C38-1))*200+(0)*500+(0)*1000)>5000,32-10,0))*500,2)) -> 38175.929 | F38: =D38+E38 -> 152423.47
B39: Mes 5 | C39: ='Clientes e Ingresos'!F10 -> 9 | D39: =$D$22 -> 114247.54 | E39: =C39*$D$27+(ROUND((((80*2+20)*0.16/1000+(80*2+20)*32/1000000*0.12)*500),2)+80*2*(4000*0.4+300*1.6)/1000000*500+MAX(0,C39-1)*(ROUND((((200*2+20)*0.16/1000+(200*2+20)*32/1000000*0.12)*500),2)+200*2*(4000*0.4+300*1.6)/1000000*500))+C39*$D$29+'Clientes e Ingresos'!D10*(8*(496838.17/30/8))+(ROUND((MAX(0,((1)*1+(MAX(0,C39-1))*3+(0)*8+(0)*16)-100)*0.0213+MAX(0,((1)*1.056+(MAX(0,C39-1))*2.63999999999999+(0)*6.6+(0)*13.2)-250)*0.09+(MAX(0,ROUNDUP((((1)*0.06+(MAX(0,C39-1))*0.15)+((0)*0.375+(0)*0.75)*0.05)*2,0)-8)+((1)*0+(MAX(0,C39-1))*0+(0)*0+(0)*0))*0.125+IF(((1)*80+(MAX(0,C39-1))*200)<=2000,10,IF(((1)*80+(MAX(0,C39-1))*200)<=5000,15,IF(((1)*80+(MAX(0,C39-1))*200)<=10000,60,110)))-10)*500,2)+ROUND((MAX(0,((1)*0.166864+(MAX(0,C39-1))*0.41716+(0)*1.0429+(0)*2.0858)+20*2*2*0.0035+30*(1/3600*0.128+5/3600*0.0106)-20)+IF(AND(((1)*55680+(MAX(0,C39-1))*139200+(0)*348000+(0)*696000)<=1000000,((1)*1.536+(MAX(0,C39-1))*3.84+(0)*9.6+(0)*19.2)<=1000),0,IF(((1)*55680+(MAX(0,C39-1))*139200+(0)*348000+(0)*696000)<=10000000,20,IF(((1)*55680+(MAX(0,C39-1))*139200+(0)*348000+(0)*696000)<=50000000,100,300)))+MAX(0,ROUNDUP(((1)*80+(MAX(0,C39-1))*200+(0)*500+(0)*1000)/5000,0)-1)*25+IF(((1)*80+(MAX(0,C39-1))*200+(0)*500+(0)*1000)>5000,32-10,0))*500,2)) -> 39661.418 | F39: =D39+E39 -> 153908.96
B40: Mes 6 | C40: ='Clientes e Ingresos'!F11 -> 9 | D40: =$D$22 -> 114247.54 | E40: =C40*$D$27+(ROUND((((80*2+20)*0.16/1000+(80*2+20)*32/1000000*0.12)*500),2)+80*2*(4000*0.4+300*1.6)/1000000*500+MAX(0,C40-1)*(ROUND((((200*2+20)*0.16/1000+(200*2+20)*32/1000000*0.12)*500),2)+200*2*(4000*0.4+300*1.6)/1000000*500))+C40*$D$29+'Clientes e Ingresos'!D11*(8*(496838.17/30/8))+(ROUND((MAX(0,((1)*1+(MAX(0,C40-1))*3+(0)*8+(0)*16)-100)*0.0213+MAX(0,((1)*1.056+(MAX(0,C40-1))*2.63999999999999+(0)*6.6+(0)*13.2)-250)*0.09+(MAX(0,ROUNDUP((((1)*0.06+(MAX(0,C40-1))*0.15)+((0)*0.375+(0)*0.75)*0.05)*2,0)-8)+((1)*0+(MAX(0,C40-1))*0+(0)*0+(0)*0))*0.125+IF(((1)*80+(MAX(0,C40-1))*200)<=2000,10,IF(((1)*80+(MAX(0,C40-1))*200)<=5000,15,IF(((1)*80+(MAX(0,C40-1))*200)<=10000,60,110)))-10)*500,2)+ROUND((MAX(0,((1)*0.166864+(MAX(0,C40-1))*0.41716+(0)*1.0429+(0)*2.0858)+20*2*2*0.0035+30*(1/3600*0.128+5/3600*0.0106)-20)+IF(AND(((1)*55680+(MAX(0,C40-1))*139200+(0)*348000+(0)*696000)<=1000000,((1)*1.536+(MAX(0,C40-1))*3.84+(0)*9.6+(0)*19.2)<=1000),0,IF(((1)*55680+(MAX(0,C40-1))*139200+(0)*348000+(0)*696000)<=10000000,20,IF(((1)*55680+(MAX(0,C40-1))*139200+(0)*348000+(0)*696000)<=50000000,100,300)))+MAX(0,ROUNDUP(((1)*80+(MAX(0,C40-1))*200+(0)*500+(0)*1000)/5000,0)-1)*25+IF(((1)*80+(MAX(0,C40-1))*200+(0)*500+(0)*1000)>5000,32-10,0))*500,2)) -> 39661.418 | F40: =D40+E40 -> 153908.96
B41: Mes 7 | C41: ='Clientes e Ingresos'!F12 -> 10 | D41: =$D$22 -> 114247.54 | E41: =C41*$D$27+(ROUND((((80*2+20)*0.16/1000+(80*2+20)*32/1000000*0.12)*500),2)+80*2*(4000*0.4+300*1.6)/1000000*500+MAX(0,C41-1)*(ROUND((((200*2+20)*0.16/1000+(200*2+20)*32/1000000*0.12)*500),2)+200*2*(4000*0.4+300*1.6)/1000000*500))+C41*$D$29+'Clientes e Ingresos'!D12*(8*(496838.17/30/8))+(ROUND((MAX(0,((1)*1+(MAX(0,C41-1))*3+(0)*8+(0)*16)-100)*0.0213+MAX(0,((1)*1.056+(MAX(0,C41-1))*2.63999999999999+(0)*6.6+(0)*13.2)-250)*0.09+(MAX(0,ROUNDUP((((1)*0.06+(MAX(0,C41-1))*0.15)+((0)*0.375+(0)*0.75)*0.05)*2,0)-8)+((1)*0+(MAX(0,C41-1))*0+(0)*0+(0)*0))*0.125+IF(((1)*80+(MAX(0,C41-1))*200)<=2000,10,IF(((1)*80+(MAX(0,C41-1))*200)<=5000,15,IF(((1)*80+(MAX(0,C41-1))*200)<=10000,60,110)))-10)*500,2)+ROUND((MAX(0,((1)*0.166864+(MAX(0,C41-1))*0.41716+(0)*1.0429+(0)*2.0858)+20*2*2*0.0035+30*(1/3600*0.128+5/3600*0.0106)-20)+IF(AND(((1)*55680+(MAX(0,C41-1))*139200+(0)*348000+(0)*696000)<=1000000,((1)*1.536+(MAX(0,C41-1))*3.84+(0)*9.6+(0)*19.2)<=1000),0,IF(((1)*55680+(MAX(0,C41-1))*139200+(0)*348000+(0)*696000)<=10000000,20,IF(((1)*55680+(MAX(0,C41-1))*139200+(0)*348000+(0)*696000)<=50000000,100,300)))+MAX(0,ROUNDUP(((1)*80+(MAX(0,C41-1))*200+(0)*500+(0)*1000)/5000,0)-1)*25+IF(((1)*80+(MAX(0,C41-1))*200+(0)*500+(0)*1000)>5000,32-10,0))*500,2)) -> 41146.908 | F41: =D41+E41 -> 155394.45
B42: Mes 8 | C42: ='Clientes e Ingresos'!F13 -> 11 | D42: =$D$22 -> 114247.54 | E42: =C42*$D$27+(ROUND((((80*2+20)*0.16/1000+(80*2+20)*32/1000000*0.12)*500),2)+80*2*(4000*0.4+300*1.6)/1000000*500+MAX(0,C42-1)*(ROUND((((200*2+20)*0.16/1000+(200*2+20)*32/1000000*0.12)*500),2)+200*2*(4000*0.4+300*1.6)/1000000*500))+C42*$D$29+'Clientes e Ingresos'!D13*(8*(496838.17/30/8))+(ROUND((MAX(0,((1)*1+(MAX(0,C42-1))*3+(0)*8+(0)*16)-100)*0.0213+MAX(0,((1)*1.056+(MAX(0,C42-1))*2.63999999999999+(0)*6.6+(0)*13.2)-250)*0.09+(MAX(0,ROUNDUP((((1)*0.06+(MAX(0,C42-1))*0.15)+((0)*0.375+(0)*0.75)*0.05)*2,0)-8)+((1)*0+(MAX(0,C42-1))*0+(0)*0+(0)*0))*0.125+IF(((1)*80+(MAX(0,C42-1))*200)<=2000,10,IF(((1)*80+(MAX(0,C42-1))*200)<=5000,15,IF(((1)*80+(MAX(0,C42-1))*200)<=10000,60,110)))-10)*500,2)+ROUND((MAX(0,((1)*0.166864+(MAX(0,C42-1))*0.41716+(0)*1.0429+(0)*2.0858)+20*2*2*0.0035+30*(1/3600*0.128+5/3600*0.0106)-20)+IF(AND(((1)*55680+(MAX(0,C42-1))*139200+(0)*348000+(0)*696000)<=1000000,((1)*1.536+(MAX(0,C42-1))*3.84+(0)*9.6+(0)*19.2)<=1000),0,IF(((1)*55680+(MAX(0,C42-1))*139200+(0)*348000+(0)*696000)<=10000000,20,IF(((1)*55680+(MAX(0,C42-1))*139200+(0)*348000+(0)*696000)<=50000000,100,300)))+MAX(0,ROUNDUP(((1)*80+(MAX(0,C42-1))*200+(0)*500+(0)*1000)/5000,0)-1)*25+IF(((1)*80+(MAX(0,C42-1))*200+(0)*500+(0)*1000)>5000,32-10,0))*500,2)) -> 45132.397 | F42: =D42+E42 -> 159379.94
B43: Mes 9 | C43: ='Clientes e Ingresos'!F14 -> 12 | D43: =$D$22 -> 114247.54 | E43: =C43*$D$27+(ROUND((((80*2+20)*0.16/1000+(80*2+20)*32/1000000*0.12)*500),2)+80*2*(4000*0.4+300*1.6)/1000000*500+MAX(0,C43-1)*(ROUND((((200*2+20)*0.16/1000+(200*2+20)*32/1000000*0.12)*500),2)+200*2*(4000*0.4+300*1.6)/1000000*500))+C43*$D$29+'Clientes e Ingresos'!D14*(8*(496838.17/30/8))+(ROUND((MAX(0,((1)*1+(MAX(0,C43-1))*3+(0)*8+(0)*16)-100)*0.0213+MAX(0,((1)*1.056+(MAX(0,C43-1))*2.63999999999999+(0)*6.6+(0)*13.2)-250)*0.09+(MAX(0,ROUNDUP((((1)*0.06+(MAX(0,C43-1))*0.15)+((0)*0.375+(0)*0.75)*0.05)*2,0)-8)+((1)*0+(MAX(0,C43-1))*0+(0)*0+(0)*0))*0.125+IF(((1)*80+(MAX(0,C43-1))*200)<=2000,10,IF(((1)*80+(MAX(0,C43-1))*200)<=5000,15,IF(((1)*80+(MAX(0,C43-1))*200)<=10000,60,110)))-10)*500,2)+ROUND((MAX(0,((1)*0.166864+(MAX(0,C43-1))*0.41716+(0)*1.0429+(0)*2.0858)+20*2*2*0.0035+30*(1/3600*0.128+5/3600*0.0106)-20)+IF(AND(((1)*55680+(MAX(0,C43-1))*139200+(0)*348000+(0)*696000)<=1000000,((1)*1.536+(MAX(0,C43-1))*3.84+(0)*9.6+(0)*19.2)<=1000),0,IF(((1)*55680+(MAX(0,C43-1))*139200+(0)*348000+(0)*696000)<=10000000,20,IF(((1)*55680+(MAX(0,C43-1))*139200+(0)*348000+(0)*696000)<=50000000,100,300)))+MAX(0,ROUNDUP(((1)*80+(MAX(0,C43-1))*200+(0)*500+(0)*1000)/5000,0)-1)*25+IF(((1)*80+(MAX(0,C43-1))*200+(0)*500+(0)*1000)>5000,32-10,0))*500,2)) -> 46617.887 | F43: =D43+E43 -> 160865.43
B44: Mes 10 | C44: ='Clientes e Ingresos'!F15 -> 12 | D44: =$D$22 -> 114247.54 | E44: =C44*$D$27+(ROUND((((80*2+20)*0.16/1000+(80*2+20)*32/1000000*0.12)*500),2)+80*2*(4000*0.4+300*1.6)/1000000*500+MAX(0,C44-1)*(ROUND((((200*2+20)*0.16/1000+(200*2+20)*32/1000000*0.12)*500),2)+200*2*(4000*0.4+300*1.6)/1000000*500))+C44*$D$29+'Clientes e Ingresos'!D15*(8*(496838.17/30/8))+(ROUND((MAX(0,((1)*1+(MAX(0,C44-1))*3+(0)*8+(0)*16)-100)*0.0213+MAX(0,((1)*1.056+(MAX(0,C44-1))*2.63999999999999+(0)*6.6+(0)*13.2)-250)*0.09+(MAX(0,ROUNDUP((((1)*0.06+(MAX(0,C44-1))*0.15)+((0)*0.375+(0)*0.75)*0.05)*2,0)-8)+((1)*0+(MAX(0,C44-1))*0+(0)*0+(0)*0))*0.125+IF(((1)*80+(MAX(0,C44-1))*200)<=2000,10,IF(((1)*80+(MAX(0,C44-1))*200)<=5000,15,IF(((1)*80+(MAX(0,C44-1))*200)<=10000,60,110)))-10)*500,2)+ROUND((MAX(0,((1)*0.166864+(MAX(0,C44-1))*0.41716+(0)*1.0429+(0)*2.0858)+20*2*2*0.0035+30*(1/3600*0.128+5/3600*0.0106)-20)+IF(AND(((1)*55680+(MAX(0,C44-1))*139200+(0)*348000+(0)*696000)<=1000000,((1)*1.536+(MAX(0,C44-1))*3.84+(0)*9.6+(0)*19.2)<=1000),0,IF(((1)*55680+(MAX(0,C44-1))*139200+(0)*348000+(0)*696000)<=10000000,20,IF(((1)*55680+(MAX(0,C44-1))*139200+(0)*348000+(0)*696000)<=50000000,100,300)))+MAX(0,ROUNDUP(((1)*80+(MAX(0,C44-1))*200+(0)*500+(0)*1000)/5000,0)-1)*25+IF(((1)*80+(MAX(0,C44-1))*200+(0)*500+(0)*1000)>5000,32-10,0))*500,2)) -> 46617.887 | F44: =D44+E44 -> 160865.43
B45: Mes 11 | C45: ='Clientes e Ingresos'!F16 -> 13 | D45: =$D$22 -> 114247.54 | E45: =C45*$D$27+(ROUND((((80*2+20)*0.16/1000+(80*2+20)*32/1000000*0.12)*500),2)+80*2*(4000*0.4+300*1.6)/1000000*500+MAX(0,C45-1)*(ROUND((((200*2+20)*0.16/1000+(200*2+20)*32/1000000*0.12)*500),2)+200*2*(4000*0.4+300*1.6)/1000000*500))+C45*$D$29+'Clientes e Ingresos'!D16*(8*(496838.17/30/8))+(ROUND((MAX(0,((1)*1+(MAX(0,C45-1))*3+(0)*8+(0)*16)-100)*0.0213+MAX(0,((1)*1.056+(MAX(0,C45-1))*2.63999999999999+(0)*6.6+(0)*13.2)-250)*0.09+(MAX(0,ROUNDUP((((1)*0.06+(MAX(0,C45-1))*0.15)+((0)*0.375+(0)*0.75)*0.05)*2,0)-8)+((1)*0+(MAX(0,C45-1))*0+(0)*0+(0)*0))*0.125+IF(((1)*80+(MAX(0,C45-1))*200)<=2000,10,IF(((1)*80+(MAX(0,C45-1))*200)<=5000,15,IF(((1)*80+(MAX(0,C45-1))*200)<=10000,60,110)))-10)*500,2)+ROUND((MAX(0,((1)*0.166864+(MAX(0,C45-1))*0.41716+(0)*1.0429+(0)*2.0858)+20*2*2*0.0035+30*(1/3600*0.128+5/3600*0.0106)-20)+IF(AND(((1)*55680+(MAX(0,C45-1))*139200+(0)*348000+(0)*696000)<=1000000,((1)*1.536+(MAX(0,C45-1))*3.84+(0)*9.6+(0)*19.2)<=1000),0,IF(((1)*55680+(MAX(0,C45-1))*139200+(0)*348000+(0)*696000)<=10000000,20,IF(((1)*55680+(MAX(0,C45-1))*139200+(0)*348000+(0)*696000)<=50000000,100,300)))+MAX(0,ROUNDUP(((1)*80+(MAX(0,C45-1))*200+(0)*500+(0)*1000)/5000,0)-1)*25+IF(((1)*80+(MAX(0,C45-1))*200+(0)*500+(0)*1000)>5000,32-10,0))*500,2)) -> 48103.376 | F45: =D45+E45 -> 162350.92
B46: Mes 12 | C46: ='Clientes e Ingresos'!F17 -> 14 | D46: =$D$22 -> 114247.54 | E46: =C46*$D$27+(ROUND((((80*2+20)*0.16/1000+(80*2+20)*32/1000000*0.12)*500),2)+80*2*(4000*0.4+300*1.6)/1000000*500+MAX(0,C46-1)*(ROUND((((200*2+20)*0.16/1000+(200*2+20)*32/1000000*0.12)*500),2)+200*2*(4000*0.4+300*1.6)/1000000*500))+C46*$D$29+'Clientes e Ingresos'!D17*(8*(496838.17/30/8))+(ROUND((MAX(0,((1)*1+(MAX(0,C46-1))*3+(0)*8+(0)*16)-100)*0.0213+MAX(0,((1)*1.056+(MAX(0,C46-1))*2.63999999999999+(0)*6.6+(0)*13.2)-250)*0.09+(MAX(0,ROUNDUP((((1)*0.06+(MAX(0,C46-1))*0.15)+((0)*0.375+(0)*0.75)*0.05)*2,0)-8)+((1)*0+(MAX(0,C46-1))*0+(0)*0+(0)*0))*0.125+IF(((1)*80+(MAX(0,C46-1))*200)<=2000,10,IF(((1)*80+(MAX(0,C46-1))*200)<=5000,15,IF(((1)*80+(MAX(0,C46-1))*200)<=10000,60,110)))-10)*500,2)+ROUND((MAX(0,((1)*0.166864+(MAX(0,C46-1))*0.41716+(0)*1.0429+(0)*2.0858)+20*2*2*0.0035+30*(1/3600*0.128+5/3600*0.0106)-20)+IF(AND(((1)*55680+(MAX(0,C46-1))*139200+(0)*348000+(0)*696000)<=1000000,((1)*1.536+(MAX(0,C46-1))*3.84+(0)*9.6+(0)*19.2)<=1000),0,IF(((1)*55680+(MAX(0,C46-1))*139200+(0)*348000+(0)*696000)<=10000000,20,IF(((1)*55680+(MAX(0,C46-1))*139200+(0)*348000+(0)*696000)<=50000000,100,300)))+MAX(0,ROUNDUP(((1)*80+(MAX(0,C46-1))*200+(0)*500+(0)*1000)/5000,0)-1)*25+IF(((1)*80+(MAX(0,C46-1))*200+(0)*500+(0)*1000)>5000,32-10,0))*500,2)) -> 49588.866 | F46: =D46+E46 -> 163836.41
B47: TOTAL AÑO 1 | D47: =SUM(D35:D46) -> 1448654.4 | E47: =SUM(E35:E46) -> 536566.02 | F47: =SUM(F35:F46) -> 1985220.4

Sheet Punto de Equilibrio
B2: ANÁLISIS DE PUNTO DE EQUILIBRIO
B3: Escenario: 1 Starter y el resto Pro Gym. Operación mensual; excluye instalación y desarrollo inicial.
B5: VARIABLES DE ENTRADA
B6: Precio medio de la mezcla inicial | D6: ='Clientes e Ingresos'!G6 -> 23000
B7: Costo Variable por Gimnasio (CVU) | D7: ='Egresos e Inversión'!D30 -> 1431.6375
B8: Margen de Contribución Unitario (MC = P - CVU) | D8: =D6-D7 -> 21568.362
B9: Costos Fijos Mensuales Base (CF) | D9: ='Egresos e Inversión'!D22 -> 114247.54
B11: RESULTADO DEL PUNTO DE EQUILIBRIO
B12: Umbral teórico (sin salto de nube) | D12: =(D9+('Egresos e Inversión'!D27+181.15)-('Egresos e Inversión'!D27+450.41)-15000+25000)/(25000-('Egresos e Inversión'!D27+450.41)) -> 5.2724161
B13: Gimnasios Requeridos (Redondeado) | D13: =IF(MIN(IF(G18>=0,B18,999),IF(G19>=0,B19,999),IF(G20>=0,B20,999),IF(G21>=0,B21,999),IF(G22>=0,B22,999),IF(G23>=0,B23,999),IF(G24>=0,B24,999),IF(G25>=0,B25,999),IF(G26>=0,B26,999),IF(G27>=0,B27,999),IF(G28>=0,B28,999),IF(G29>=0,B29,999),IF(G30>=0,B30,999),IF(G31>=0,B31,999),IF(G32>=0,B32,999))=999,"Fuera de tabla",MIN(IF(G18>=0,B18,999),IF(G19>=0,B19,999),IF(G20>=0,B20,999),IF(G21>=0,B21,999),IF(G22>=0,B22,999),IF(G23>=0,B23,999),IF(G24>=0,B24,999),IF(G25>=0,B25,999),IF(G26>=0,B26,999),IF(G27>=0,B27,999),IF(G28>=0,B28,999),IF(G29>=0,B29,999),IF(G30>=0,B30,999),IF(G31>=0,B31,999),IF(G32>=0,B32,999))) -> 6 | E13: Equilibrio de operación; recuperar inversión y altas requiere revisar el acumulado anual.
B14: Facturación Mínima Mensual (₡) | D14: =IF(ISNUMBER(D13),15000+MAX(0,D13-1)*25000,"Fuera de tabla") -> 140000
B16: TABLA DE SENSIBILIDAD Y RESULTADO OPERATIVO SEGÚN VOLUMEN
B17: N° Gimnasios | C17: Ingresos Totales (₡) | D17: Variables + nube (₡) | E17: Costos Fijos (₡) | F17: Egresos Totales (₡) | G17: Resultado Operativo (₡) | H17: Estado
B18: 1 | C18: =15000+MAX(0,B18-1)*25000 -> 15000 | D18: =ROUND(B18*'Egresos e Inversión'!$D$27+(ROUND((((80*2+20)*0.16/1000+(80*2+20)*32/1000000*0.12)*500),2)+80*2*(4000*0.4+300*1.6)/1000000*500+MAX(0,B18-1)*(ROUND((((200*2+20)*0.16/1000+(200*2+20)*32/1000000*0.12)*500),2)+200*2*(4000*0.4+300*1.6)/1000000*500))+B18*'Egresos e Inversión'!$D$29+(ROUND((MAX(0,((1)*1+(MAX(0,B18-1))*3+(0)*8+(0)*16)-100)*0.0213+MAX(0,((1)*1.056+(MAX(0,B18-1))*2.63999999999999+(0)*6.6+(0)*13.2)-250)*0.09+(MAX(0,ROUNDUP((((1)*0.06+(MAX(0,B18-1))*0.15)+((0)*0.375+(0)*0.75)*0.05)*2,0)-8)+((1)*0+(MAX(0,B18-1))*0+(0)*0+(0)*0))*0.125+IF(((1)*80+(MAX(0,B18-1))*200)<=2000,10,IF(((1)*80+(MAX(0,B18-1))*200)<=5000,15,IF(((1)*80+(MAX(0,B18-1))*200)<=10000,60,110)))-10)*500,2)+ROUND((MAX(0,((1)*0.166864+(MAX(0,B18-1))*0.41716+(0)*1.0429+(0)*2.0858)+20*2*2*0.0035+30*(1/3600*0.128+5/3600*0.0106)-20)+IF(AND(((1)*55680+(MAX(0,B18-1))*139200+(0)*348000+(0)*696000)<=1000000,((1)*1.536+(MAX(0,B18-1))*3.84+(0)*9.6+(0)*19.2)<=1000),0,IF(((1)*55680+(MAX(0,B18-1))*139200+(0)*348000+(0)*696000)<=10000000,20,IF(((1)*55680+(MAX(0,B18-1))*139200+(0)*348000+(0)*696000)<=50000000,100,300)))+MAX(0,ROUNDUP(((1)*80+(MAX(0,B18-1))*200+(0)*500+(0)*1000)/5000,0)-1)*25+IF(((1)*80+(MAX(0,B18-1))*200+(0)*500+(0)*1000)>5000,32-10,0))*500,2)),2) -> 1216.23 | E18: =$D$9 -> 114247.54 | F18: =D18+E18 -> 115463.77 | G18: =C18-F18 -> -100463.77 | H18: =IF(G18<0,"Pérdida",IF(G18=0,"Equilibrio","Ganancia")) -> Pérdida
B19: 2 | C19: =15000+MAX(0,B19-1)*25000 -> 40000 | D19: =ROUND(B19*'Egresos e Inversión'!$D$27+(ROUND((((80*2+20)*0.16/1000+(80*2+20)*32/1000000*0.12)*500),2)+80*2*(4000*0.4+300*1.6)/1000000*500+MAX(0,B19-1)*(ROUND((((200*2+20)*0.16/1000+(200*2+20)*32/1000000*0.12)*500),2)+200*2*(4000*0.4+300*1.6)/1000000*500))+B19*'Egresos e Inversión'!$D$29+(ROUND((MAX(0,((1)*1+(MAX(0,B19-1))*3+(0)*8+(0)*16)-100)*0.0213+MAX(0,((1)*1.056+(MAX(0,B19-1))*2.63999999999999+(0)*6.6+(0)*13.2)-250)*0.09+(MAX(0,ROUNDUP((((1)*0.06+(MAX(0,B19-1))*0.15)+((0)*0.375+(0)*0.75)*0.05)*2,0)-8)+((1)*0+(MAX(0,B19-1))*0+(0)*0+(0)*0))*0.125+IF(((1)*80+(MAX(0,B19-1))*200)<=2000,10,IF(((1)*80+(MAX(0,B19-1))*200)<=5000,15,IF(((1)*80+(MAX(0,B19-1))*200)<=10000,60,110)))-10)*500,2)+ROUND((MAX(0,((1)*0.166864+(MAX(0,B19-1))*0.41716+(0)*1.0429+(0)*2.0858)+20*2*2*0.0035+30*(1/3600*0.128+5/3600*0.0106)-20)+IF(AND(((1)*55680+(MAX(0,B19-1))*139200+(0)*348000+(0)*696000)<=1000000,((1)*1.536+(MAX(0,B19-1))*3.84+(0)*9.6+(0)*19.2)<=1000),0,IF(((1)*55680+(MAX(0,B19-1))*139200+(0)*348000+(0)*696000)<=10000000,20,IF(((1)*55680+(MAX(0,B19-1))*139200+(0)*348000+(0)*696000)<=50000000,100,300)))+MAX(0,ROUNDUP(((1)*80+(MAX(0,B19-1))*200+(0)*500+(0)*1000)/5000,0)-1)*25+IF(((1)*80+(MAX(0,B19-1))*200+(0)*500+(0)*1000)>5000,32-10,0))*500,2)),2) -> 2701.72 | E19: =$D$9 -> 114247.54 | F19: =D19+E19 -> 116949.26 | G19: =C19-F19 -> -76949.265 | H19: =IF(G19<0,"Pérdida",IF(G19=0,"Equilibrio","Ganancia")) -> Pérdida
B20: 3 | C20: =15000+MAX(0,B20-1)*25000 -> 65000 | D20: =ROUND(B20*'Egresos e Inversión'!$D$27+(ROUND((((80*2+20)*0.16/1000+(80*2+20)*32/1000000*0.12)*500),2)+80*2*(4000*0.4+300*1.6)/1000000*500+MAX(0,B20-1)*(ROUND((((200*2+20)*0.16/1000+(200*2+20)*32/1000000*0.12)*500),2)+200*2*(4000*0.4+300*1.6)/1000000*500))+B20*'Egresos e Inversión'!$D$29+(ROUND((MAX(0,((1)*1+(MAX(0,B20-1))*3+(0)*8+(0)*16)-100)*0.0213+MAX(0,((1)*1.056+(MAX(0,B20-1))*2.63999999999999+(0)*6.6+(0)*13.2)-250)*0.09+(MAX(0,ROUNDUP((((1)*0.06+(MAX(0,B20-1))*0.15)+((0)*0.375+(0)*0.75)*0.05)*2,0)-8)+((1)*0+(MAX(0,B20-1))*0+(0)*0+(0)*0))*0.125+IF(((1)*80+(MAX(0,B20-1))*200)<=2000,10,IF(((1)*80+(MAX(0,B20-1))*200)<=5000,15,IF(((1)*80+(MAX(0,B20-1))*200)<=10000,60,110)))-10)*500,2)+ROUND((MAX(0,((1)*0.166864+(MAX(0,B20-1))*0.41716+(0)*1.0429+(0)*2.0858)+20*2*2*0.0035+30*(1/3600*0.128+5/3600*0.0106)-20)+IF(AND(((1)*55680+(MAX(0,B20-1))*139200+(0)*348000+(0)*696000)<=1000000,((1)*1.536+(MAX(0,B20-1))*3.84+(0)*9.6+(0)*19.2)<=1000),0,IF(((1)*55680+(MAX(0,B20-1))*139200+(0)*348000+(0)*696000)<=10000000,20,IF(((1)*55680+(MAX(0,B20-1))*139200+(0)*348000+(0)*696000)<=50000000,100,300)))+MAX(0,ROUNDUP(((1)*80+(MAX(0,B20-1))*200+(0)*500+(0)*1000)/5000,0)-1)*25+IF(((1)*80+(MAX(0,B20-1))*200+(0)*500+(0)*1000)>5000,32-10,0))*500,2)),2) -> 4187.21 | E20: =$D$9 -> 114247.54 | F20: =D20+E20 -> 118434.75 | G20: =C20-F20 -> -53434.755 | H20: =IF(G20<0,"Pérdida",IF(G20=0,"Equilibrio","Ganancia")) -> Pérdida
B21: 4 | C21: =15000+MAX(0,B21-1)*25000 -> 90000 | D21: =ROUND(B21*'Egresos e Inversión'!$D$27+(ROUND((((80*2+20)*0.16/1000+(80*2+20)*32/1000000*0.12)*500),2)+80*2*(4000*0.4+300*1.6)/1000000*500+MAX(0,B21-1)*(ROUND((((200*2+20)*0.16/1000+(200*2+20)*32/1000000*0.12)*500),2)+200*2*(4000*0.4+300*1.6)/1000000*500))+B21*'Egresos e Inversión'!$D$29+(ROUND((MAX(0,((1)*1+(MAX(0,B21-1))*3+(0)*8+(0)*16)-100)*0.0213+MAX(0,((1)*1.056+(MAX(0,B21-1))*2.63999999999999+(0)*6.6+(0)*13.2)-250)*0.09+(MAX(0,ROUNDUP((((1)*0.06+(MAX(0,B21-1))*0.15)+((0)*0.375+(0)*0.75)*0.05)*2,0)-8)+((1)*0+(MAX(0,B21-1))*0+(0)*0+(0)*0))*0.125+IF(((1)*80+(MAX(0,B21-1))*200)<=2000,10,IF(((1)*80+(MAX(0,B21-1))*200)<=5000,15,IF(((1)*80+(MAX(0,B21-1))*200)<=10000,60,110)))-10)*500,2)+ROUND((MAX(0,((1)*0.166864+(MAX(0,B21-1))*0.41716+(0)*1.0429+(0)*2.0858)+20*2*2*0.0035+30*(1/3600*0.128+5/3600*0.0106)-20)+IF(AND(((1)*55680+(MAX(0,B21-1))*139200+(0)*348000+(0)*696000)<=1000000,((1)*1.536+(MAX(0,B21-1))*3.84+(0)*9.6+(0)*19.2)<=1000),0,IF(((1)*55680+(MAX(0,B21-1))*139200+(0)*348000+(0)*696000)<=10000000,20,IF(((1)*55680+(MAX(0,B21-1))*139200+(0)*348000+(0)*696000)<=50000000,100,300)))+MAX(0,ROUNDUP(((1)*80+(MAX(0,B21-1))*200+(0)*500+(0)*1000)/5000,0)-1)*25+IF(((1)*80+(MAX(0,B21-1))*200+(0)*500+(0)*1000)>5000,32-10,0))*500,2)),2) -> 5672.7 | E21: =$D$9 -> 114247.54 | F21: =D21+E21 -> 119920.24 | G21: =C21-F21 -> -29920.245 | H21: =IF(G21<0,"Pérdida",IF(G21=0,"Equilibrio","Ganancia")) -> Pérdida
B22: 5 | C22: =15000+MAX(0,B22-1)*25000 -> 115000 | D22: =ROUND(B22*'Egresos e Inversión'!$D$27+(ROUND((((80*2+20)*0.16/1000+(80*2+20)*32/1000000*0.12)*500),2)+80*2*(4000*0.4+300*1.6)/1000000*500+MAX(0,B22-1)*(ROUND((((200*2+20)*0.16/1000+(200*2+20)*32/1000000*0.12)*500),2)+200*2*(4000*0.4+300*1.6)/1000000*500))+B22*'Egresos e Inversión'!$D$29+(ROUND((MAX(0,((1)*1+(MAX(0,B22-1))*3+(0)*8+(0)*16)-100)*0.0213+MAX(0,((1)*1.056+(MAX(0,B22-1))*2.63999999999999+(0)*6.6+(0)*13.2)-250)*0.09+(MAX(0,ROUNDUP((((1)*0.06+(MAX(0,B22-1))*0.15)+((0)*0.375+(0)*0.75)*0.05)*2,0)-8)+((1)*0+(MAX(0,B22-1))*0+(0)*0+(0)*0))*0.125+IF(((1)*80+(MAX(0,B22-1))*200)<=2000,10,IF(((1)*80+(MAX(0,B22-1))*200)<=5000,15,IF(((1)*80+(MAX(0,B22-1))*200)<=10000,60,110)))-10)*500,2)+ROUND((MAX(0,((1)*0.166864+(MAX(0,B22-1))*0.41716+(0)*1.0429+(0)*2.0858)+20*2*2*0.0035+30*(1/3600*0.128+5/3600*0.0106)-20)+IF(AND(((1)*55680+(MAX(0,B22-1))*139200+(0)*348000+(0)*696000)<=1000000,((1)*1.536+(MAX(0,B22-1))*3.84+(0)*9.6+(0)*19.2)<=1000),0,IF(((1)*55680+(MAX(0,B22-1))*139200+(0)*348000+(0)*696000)<=10000000,20,IF(((1)*55680+(MAX(0,B22-1))*139200+(0)*348000+(0)*696000)<=50000000,100,300)))+MAX(0,ROUNDUP(((1)*80+(MAX(0,B22-1))*200+(0)*500+(0)*1000)/5000,0)-1)*25+IF(((1)*80+(MAX(0,B22-1))*200+(0)*500+(0)*1000)>5000,32-10,0))*500,2)),2) -> 7158.19 | E22: =$D$9 -> 114247.54 | F22: =D22+E22 -> 121405.73 | G22: =C22-F22 -> -6405.7347 | H22: =IF(G22<0,"Pérdida",IF(G22=0,"Equilibrio","Ganancia")) -> Pérdida
B23: 6 | C23: =15000+MAX(0,B23-1)*25000 -> 140000 | D23: =ROUND(B23*'Egresos e Inversión'!$D$27+(ROUND((((80*2+20)*0.16/1000+(80*2+20)*32/1000000*0.12)*500),2)+80*2*(4000*0.4+300*1.6)/1000000*500+MAX(0,B23-1)*(ROUND((((200*2+20)*0.16/1000+(200*2+20)*32/1000000*0.12)*500),2)+200*2*(4000*0.4+300*1.6)/1000000*500))+B23*'Egresos e Inversión'!$D$29+(ROUND((MAX(0,((1)*1+(MAX(0,B23-1))*3+(0)*8+(0)*16)-100)*0.0213+MAX(0,((1)*1.056+(MAX(0,B23-1))*2.63999999999999+(0)*6.6+(0)*13.2)-250)*0.09+(MAX(0,ROUNDUP((((1)*0.06+(MAX(0,B23-1))*0.15)+((0)*0.375+(0)*0.75)*0.05)*2,0)-8)+((1)*0+(MAX(0,B23-1))*0+(0)*0+(0)*0))*0.125+IF(((1)*80+(MAX(0,B23-1))*200)<=2000,10,IF(((1)*80+(MAX(0,B23-1))*200)<=5000,15,IF(((1)*80+(MAX(0,B23-1))*200)<=10000,60,110)))-10)*500,2)+ROUND((MAX(0,((1)*0.166864+(MAX(0,B23-1))*0.41716+(0)*1.0429+(0)*2.0858)+20*2*2*0.0035+30*(1/3600*0.128+5/3600*0.0106)-20)+IF(AND(((1)*55680+(MAX(0,B23-1))*139200+(0)*348000+(0)*696000)<=1000000,((1)*1.536+(MAX(0,B23-1))*3.84+(0)*9.6+(0)*19.2)<=1000),0,IF(((1)*55680+(MAX(0,B23-1))*139200+(0)*348000+(0)*696000)<=10000000,20,IF(((1)*55680+(MAX(0,B23-1))*139200+(0)*348000+(0)*696000)<=50000000,100,300)))+MAX(0,ROUNDUP(((1)*80+(MAX(0,B23-1))*200+(0)*500+(0)*1000)/5000,0)-1)*25+IF(((1)*80+(MAX(0,B23-1))*200+(0)*500+(0)*1000)>5000,32-10,0))*500,2)),2) -> 8643.68 | E23: =$D$9 -> 114247.54 | F23: =D23+E23 -> 122891.22 | G23: =C23-F23 -> 17108.775 | H23: =IF(G23<0,"Pérdida",IF(G23=0,"Equilibrio","Ganancia")) -> Ganancia
B24: 7 | C24: =15000+MAX(0,B24-1)*25000 -> 165000 | D24: =ROUND(B24*'Egresos e Inversión'!$D$27+(ROUND((((80*2+20)*0.16/1000+(80*2+20)*32/1000000*0.12)*500),2)+80*2*(4000*0.4+300*1.6)/1000000*500+MAX(0,B24-1)*(ROUND((((200*2+20)*0.16/1000+(200*2+20)*32/1000000*0.12)*500),2)+200*2*(4000*0.4+300*1.6)/1000000*500))+B24*'Egresos e Inversión'!$D$29+(ROUND((MAX(0,((1)*1+(MAX(0,B24-1))*3+(0)*8+(0)*16)-100)*0.0213+MAX(0,((1)*1.056+(MAX(0,B24-1))*2.63999999999999+(0)*6.6+(0)*13.2)-250)*0.09+(MAX(0,ROUNDUP((((1)*0.06+(MAX(0,B24-1))*0.15)+((0)*0.375+(0)*0.75)*0.05)*2,0)-8)+((1)*0+(MAX(0,B24-1))*0+(0)*0+(0)*0))*0.125+IF(((1)*80+(MAX(0,B24-1))*200)<=2000,10,IF(((1)*80+(MAX(0,B24-1))*200)<=5000,15,IF(((1)*80+(MAX(0,B24-1))*200)<=10000,60,110)))-10)*500,2)+ROUND((MAX(0,((1)*0.166864+(MAX(0,B24-1))*0.41716+(0)*1.0429+(0)*2.0858)+20*2*2*0.0035+30*(1/3600*0.128+5/3600*0.0106)-20)+IF(AND(((1)*55680+(MAX(0,B24-1))*139200+(0)*348000+(0)*696000)<=1000000,((1)*1.536+(MAX(0,B24-1))*3.84+(0)*9.6+(0)*19.2)<=1000),0,IF(((1)*55680+(MAX(0,B24-1))*139200+(0)*348000+(0)*696000)<=10000000,20,IF(((1)*55680+(MAX(0,B24-1))*139200+(0)*348000+(0)*696000)<=50000000,100,300)))+MAX(0,ROUNDUP(((1)*80+(MAX(0,B24-1))*200+(0)*500+(0)*1000)/5000,0)-1)*25+IF(((1)*80+(MAX(0,B24-1))*200+(0)*500+(0)*1000)>5000,32-10,0))*500,2)),2) -> 10129.17 | E24: =$D$9 -> 114247.54 | F24: =D24+E24 -> 124376.71 | G24: =C24-F24 -> 40623.285 | H24: =IF(G24<0,"Pérdida",IF(G24=0,"Equilibrio","Ganancia")) -> Ganancia
B25: 8 | C25: =15000+MAX(0,B25-1)*25000 -> 190000 | D25: =ROUND(B25*'Egresos e Inversión'!$D$27+(ROUND((((80*2+20)*0.16/1000+(80*2+20)*32/1000000*0.12)*500),2)+80*2*(4000*0.4+300*1.6)/1000000*500+MAX(0,B25-1)*(ROUND((((200*2+20)*0.16/1000+(200*2+20)*32/1000000*0.12)*500),2)+200*2*(4000*0.4+300*1.6)/1000000*500))+B25*'Egresos e Inversión'!$D$29+(ROUND((MAX(0,((1)*1+(MAX(0,B25-1))*3+(0)*8+(0)*16)-100)*0.0213+MAX(0,((1)*1.056+(MAX(0,B25-1))*2.63999999999999+(0)*6.6+(0)*13.2)-250)*0.09+(MAX(0,ROUNDUP((((1)*0.06+(MAX(0,B25-1))*0.15)+((0)*0.375+(0)*0.75)*0.05)*2,0)-8)+((1)*0+(MAX(0,B25-1))*0+(0)*0+(0)*0))*0.125+IF(((1)*80+(MAX(0,B25-1))*200)<=2000,10,IF(((1)*80+(MAX(0,B25-1))*200)<=5000,15,IF(((1)*80+(MAX(0,B25-1))*200)<=10000,60,110)))-10)*500,2)+ROUND((MAX(0,((1)*0.166864+(MAX(0,B25-1))*0.41716+(0)*1.0429+(0)*2.0858)+20*2*2*0.0035+30*(1/3600*0.128+5/3600*0.0106)-20)+IF(AND(((1)*55680+(MAX(0,B25-1))*139200+(0)*348000+(0)*696000)<=1000000,((1)*1.536+(MAX(0,B25-1))*3.84+(0)*9.6+(0)*19.2)<=1000),0,IF(((1)*55680+(MAX(0,B25-1))*139200+(0)*348000+(0)*696000)<=10000000,20,IF(((1)*55680+(MAX(0,B25-1))*139200+(0)*348000+(0)*696000)<=50000000,100,300)))+MAX(0,ROUNDUP(((1)*80+(MAX(0,B25-1))*200+(0)*500+(0)*1000)/5000,0)-1)*25+IF(((1)*80+(MAX(0,B25-1))*200+(0)*500+(0)*1000)>5000,32-10,0))*500,2)),2) -> 21614.66 | E25: =$D$9 -> 114247.54 | F25: =D25+E25 -> 135862.2 | G25: =C25-F25 -> 54137.795 | H25: =IF(G25<0,"Pérdida",IF(G25=0,"Equilibrio","Ganancia")) -> Ganancia
B26: 9 | C26: =15000+MAX(0,B26-1)*25000 -> 215000 | D26: =ROUND(B26*'Egresos e Inversión'!$D$27+(ROUND((((80*2+20)*0.16/1000+(80*2+20)*32/1000000*0.12)*500),2)+80*2*(4000*0.4+300*1.6)/1000000*500+MAX(0,B26-1)*(ROUND((((200*2+20)*0.16/1000+(200*2+20)*32/1000000*0.12)*500),2)+200*2*(4000*0.4+300*1.6)/1000000*500))+B26*'Egresos e Inversión'!$D$29+(ROUND((MAX(0,((1)*1+(MAX(0,B26-1))*3+(0)*8+(0)*16)-100)*0.0213+MAX(0,((1)*1.056+(MAX(0,B26-1))*2.63999999999999+(0)*6.6+(0)*13.2)-250)*0.09+(MAX(0,ROUNDUP((((1)*0.06+(MAX(0,B26-1))*0.15)+((0)*0.375+(0)*0.75)*0.05)*2,0)-8)+((1)*0+(MAX(0,B26-1))*0+(0)*0+(0)*0))*0.125+IF(((1)*80+(MAX(0,B26-1))*200)<=2000,10,IF(((1)*80+(MAX(0,B26-1))*200)<=5000,15,IF(((1)*80+(MAX(0,B26-1))*200)<=10000,60,110)))-10)*500,2)+ROUND((MAX(0,((1)*0.166864+(MAX(0,B26-1))*0.41716+(0)*1.0429+(0)*2.0858)+20*2*2*0.0035+30*(1/3600*0.128+5/3600*0.0106)-20)+IF(AND(((1)*55680+(MAX(0,B26-1))*139200+(0)*348000+(0)*696000)<=1000000,((1)*1.536+(MAX(0,B26-1))*3.84+(0)*9.6+(0)*19.2)<=1000),0,IF(((1)*55680+(MAX(0,B26-1))*139200+(0)*348000+(0)*696000)<=10000000,20,IF(((1)*55680+(MAX(0,B26-1))*139200+(0)*348000+(0)*696000)<=50000000,100,300)))+MAX(0,ROUNDUP(((1)*80+(MAX(0,B26-1))*200+(0)*500+(0)*1000)/5000,0)-1)*25+IF(((1)*80+(MAX(0,B26-1))*200+(0)*500+(0)*1000)>5000,32-10,0))*500,2)),2) -> 23100.15 | E26: =$D$9 -> 114247.54 | F26: =D26+E26 -> 137347.69 | G26: =C26-F26 -> 77652.305 | H26: =IF(G26<0,"Pérdida",IF(G26=0,"Equilibrio","Ganancia")) -> Ganancia
B27: 10 | C27: =15000+MAX(0,B27-1)*25000 -> 240000 | D27: =ROUND(B27*'Egresos e Inversión'!$D$27+(ROUND((((80*2+20)*0.16/1000+(80*2+20)*32/1000000*0.12)*500),2)+80*2*(4000*0.4+300*1.6)/1000000*500+MAX(0,B27-1)*(ROUND((((200*2+20)*0.16/1000+(200*2+20)*32/1000000*0.12)*500),2)+200*2*(4000*0.4+300*1.6)/1000000*500))+B27*'Egresos e Inversión'!$D$29+(ROUND((MAX(0,((1)*1+(MAX(0,B27-1))*3+(0)*8+(0)*16)-100)*0.0213+MAX(0,((1)*1.056+(MAX(0,B27-1))*2.63999999999999+(0)*6.6+(0)*13.2)-250)*0.09+(MAX(0,ROUNDUP((((1)*0.06+(MAX(0,B27-1))*0.15)+((0)*0.375+(0)*0.75)*0.05)*2,0)-8)+((1)*0+(MAX(0,B27-1))*0+(0)*0+(0)*0))*0.125+IF(((1)*80+(MAX(0,B27-1))*200)<=2000,10,IF(((1)*80+(MAX(0,B27-1))*200)<=5000,15,IF(((1)*80+(MAX(0,B27-1))*200)<=10000,60,110)))-10)*500,2)+ROUND((MAX(0,((1)*0.166864+(MAX(0,B27-1))*0.41716+(0)*1.0429+(0)*2.0858)+20*2*2*0.0035+30*(1/3600*0.128+5/3600*0.0106)-20)+IF(AND(((1)*55680+(MAX(0,B27-1))*139200+(0)*348000+(0)*696000)<=1000000,((1)*1.536+(MAX(0,B27-1))*3.84+(0)*9.6+(0)*19.2)<=1000),0,IF(((1)*55680+(MAX(0,B27-1))*139200+(0)*348000+(0)*696000)<=10000000,20,IF(((1)*55680+(MAX(0,B27-1))*139200+(0)*348000+(0)*696000)<=50000000,100,300)))+MAX(0,ROUNDUP(((1)*80+(MAX(0,B27-1))*200+(0)*500+(0)*1000)/5000,0)-1)*25+IF(((1)*80+(MAX(0,B27-1))*200+(0)*500+(0)*1000)>5000,32-10,0))*500,2)),2) -> 24585.64 | E27: =$D$9 -> 114247.54 | F27: =D27+E27 -> 138833.18 | G27: =C27-F27 -> 101166.82 | H27: =IF(G27<0,"Pérdida",IF(G27=0,"Equilibrio","Ganancia")) -> Ganancia
B28: 11 | C28: =15000+MAX(0,B28-1)*25000 -> 265000 | D28: =ROUND(B28*'Egresos e Inversión'!$D$27+(ROUND((((80*2+20)*0.16/1000+(80*2+20)*32/1000000*0.12)*500),2)+80*2*(4000*0.4+300*1.6)/1000000*500+MAX(0,B28-1)*(ROUND((((200*2+20)*0.16/1000+(200*2+20)*32/1000000*0.12)*500),2)+200*2*(4000*0.4+300*1.6)/1000000*500))+B28*'Egresos e Inversión'!$D$29+(ROUND((MAX(0,((1)*1+(MAX(0,B28-1))*3+(0)*8+(0)*16)-100)*0.0213+MAX(0,((1)*1.056+(MAX(0,B28-1))*2.63999999999999+(0)*6.6+(0)*13.2)-250)*0.09+(MAX(0,ROUNDUP((((1)*0.06+(MAX(0,B28-1))*0.15)+((0)*0.375+(0)*0.75)*0.05)*2,0)-8)+((1)*0+(MAX(0,B28-1))*0+(0)*0+(0)*0))*0.125+IF(((1)*80+(MAX(0,B28-1))*200)<=2000,10,IF(((1)*80+(MAX(0,B28-1))*200)<=5000,15,IF(((1)*80+(MAX(0,B28-1))*200)<=10000,60,110)))-10)*500,2)+ROUND((MAX(0,((1)*0.166864+(MAX(0,B28-1))*0.41716+(0)*1.0429+(0)*2.0858)+20*2*2*0.0035+30*(1/3600*0.128+5/3600*0.0106)-20)+IF(AND(((1)*55680+(MAX(0,B28-1))*139200+(0)*348000+(0)*696000)<=1000000,((1)*1.536+(MAX(0,B28-1))*3.84+(0)*9.6+(0)*19.2)<=1000),0,IF(((1)*55680+(MAX(0,B28-1))*139200+(0)*348000+(0)*696000)<=10000000,20,IF(((1)*55680+(MAX(0,B28-1))*139200+(0)*348000+(0)*696000)<=50000000,100,300)))+MAX(0,ROUNDUP(((1)*80+(MAX(0,B28-1))*200+(0)*500+(0)*1000)/5000,0)-1)*25+IF(((1)*80+(MAX(0,B28-1))*200+(0)*500+(0)*1000)>5000,32-10,0))*500,2)),2) -> 28571.12 | E28: =$D$9 -> 114247.54 | F28: =D28+E28 -> 142818.66 | G28: =C28-F28 -> 122181.34 | H28: =IF(G28<0,"Pérdida",IF(G28=0,"Equilibrio","Ganancia")) -> Ganancia
B29: 12 | C29: =15000+MAX(0,B29-1)*25000 -> 290000 | D29: =ROUND(B29*'Egresos e Inversión'!$D$27+(ROUND((((80*2+20)*0.16/1000+(80*2+20)*32/1000000*0.12)*500),2)+80*2*(4000*0.4+300*1.6)/1000000*500+MAX(0,B29-1)*(ROUND((((200*2+20)*0.16/1000+(200*2+20)*32/1000000*0.12)*500),2)+200*2*(4000*0.4+300*1.6)/1000000*500))+B29*'Egresos e Inversión'!$D$29+(ROUND((MAX(0,((1)*1+(MAX(0,B29-1))*3+(0)*8+(0)*16)-100)*0.0213+MAX(0,((1)*1.056+(MAX(0,B29-1))*2.63999999999999+(0)*6.6+(0)*13.2)-250)*0.09+(MAX(0,ROUNDUP((((1)*0.06+(MAX(0,B29-1))*0.15)+((0)*0.375+(0)*0.75)*0.05)*2,0)-8)+((1)*0+(MAX(0,B29-1))*0+(0)*0+(0)*0))*0.125+IF(((1)*80+(MAX(0,B29-1))*200)<=2000,10,IF(((1)*80+(MAX(0,B29-1))*200)<=5000,15,IF(((1)*80+(MAX(0,B29-1))*200)<=10000,60,110)))-10)*500,2)+ROUND((MAX(0,((1)*0.166864+(MAX(0,B29-1))*0.41716+(0)*1.0429+(0)*2.0858)+20*2*2*0.0035+30*(1/3600*0.128+5/3600*0.0106)-20)+IF(AND(((1)*55680+(MAX(0,B29-1))*139200+(0)*348000+(0)*696000)<=1000000,((1)*1.536+(MAX(0,B29-1))*3.84+(0)*9.6+(0)*19.2)<=1000),0,IF(((1)*55680+(MAX(0,B29-1))*139200+(0)*348000+(0)*696000)<=10000000,20,IF(((1)*55680+(MAX(0,B29-1))*139200+(0)*348000+(0)*696000)<=50000000,100,300)))+MAX(0,ROUNDUP(((1)*80+(MAX(0,B29-1))*200+(0)*500+(0)*1000)/5000,0)-1)*25+IF(((1)*80+(MAX(0,B29-1))*200+(0)*500+(0)*1000)>5000,32-10,0))*500,2)),2) -> 30056.61 | E29: =$D$9 -> 114247.54 | F29: =D29+E29 -> 144304.15 | G29: =C29-F29 -> 145695.85 | H29: =IF(G29<0,"Pérdida",IF(G29=0,"Equilibrio","Ganancia")) -> Ganancia
... B32: 15 | C32: =15000+MAX(0,B32-1)*25000 -> 365000 | D32: =ROUND(B32*'Egresos e Inversión'!$D$27+(ROUND((((80*2+20)*0.16/1000+(80*2+20)*32/1000000*0.12)*500),2)+80*2*(4000*0.4+300*1.6)/1000000*500+MAX(0,B32-1)*(ROUND((((200*2+20)*0.16/1000+(200*2+20)*32/1000000*0.12)*500),2)+200*2*(4000*0.4+300*1.6)/1000000*500))+B32*'Egresos e Inversión'!$D$29+(ROUND((MAX(0,((1)*1+(MAX(0,B32-1))*3+(0)*8+(0)*16)-100)*0.0213+MAX(0,((1)*1.056+(MAX(0,B32-1))*2.63999999999999+(0)*6.6+(0)*13.2)-250)*0.09+(MAX(0,ROUNDUP((((1)*0.06+(MAX(0,B32-1))*0.15)+((0)*0.375+(0)*0.75)*0.05)*2,0)-8)+((1)*0+(MAX(0,B32-1))*0+(0)*0+(0)*0))*0.125+IF(((1)*80+(MAX(0,B32-1))*200)<=2000,10,IF(((1)*80+(MAX(0,B32-1))*200)<=5000,15,IF(((1)*80+(MAX(0,B32-1))*200)<=10000,60,110)))-10)*500,2)+ROUND((MAX(0,((1)*0.166864+(MAX(0,B32-1))*0.41716+(0)*1.0429+(0)*2.0858)+20*2*2*0.0035+30*(1/3600*0.128+5/3600*0.0106)-20)+IF(AND(((1)*55680+(MAX(0,B32-1))*139200+(0)*348000+(0)*696000)<=1000000,((1)*1.536+(MAX(0,B32-1))*3.84+(0)*9.6+(0)*19.2)<=1000),0,IF(((1)*55680+(MAX(0,B32-1))*139200+(0)*348000+(0)*696000)<=10000000,20,IF(((1)*55680+(MAX(0,B32-1))*139200+(0)*348000+(0)*696000)<=50000000,100,300)))+MAX(0,ROUNDUP(((1)*80+(MAX(0,B32-1))*200+(0)*500+(0)*1000)/5000,0)-1)*25+IF(((1)*80+(MAX(0,B32-1))*200+(0)*500+(0)*1000)>5000,32-10,0))*500,2)),2) -> 34513.08 | E32: =$D$9 -> 114247.54 | F32: =D32+E32 -> 148760.62 | G32: =C32-F32 -> 216239.38 | H32: =IF(G32<0,"Pérdida",IF(G32=0,"Equilibrio","Ganancia")) -> Ganancia

Sheet Estados Financieros
B2: ESTADOS FINANCIEROS PROYECTADOS (AÑO 1)
B3: Flujo: solo efectivo. Resultado: incluye trabajo aportado. Renta 0 bajo formalización MYPE; no es beneficio confirmado.
B5: 1. FLUJO DE EFECTIVO (TRABAJO PROPIO SIN PAGO)
B6: Concepto / Mes | C6: Mes 1 | D6: Mes 2 | E6: Mes 3 | F6: Mes 4 | G6: Mes 5 | H6: Mes 6 | I6: Mes 7 | J6: Mes 8 | K6: Mes 9 | L6: Mes 10 | M6: Mes 11 | N6: Mes 12 | O6: Total Año 1
B7: ENTRADAS DE EFECTIVO
B8: Ingresos por Suscripciones (MRR) | C8: ='Clientes e Ingresos'!H6 -> 115000 | D8: ='Clientes e Ingresos'!H7 -> 140000 | E8: ='Clientes e Ingresos'!H8 -> 165000 | F8: ='Clientes e Ingresos'!H9 -> 190000 | G8: ='Clientes e Ingresos'!H10 -> 215000 | H8: ='Clientes e Ingresos'!H11 -> 215000 | I8: ='Clientes e Ingresos'!H12 -> 240000 | J8: ='Clientes e Ingresos'!H13 -> 265000 | K8: ='Clientes e Ingresos'!H14 -> 290000 | L8: ='Clientes e Ingresos'!H15 -> 290000 | M8: ='Clientes e Ingresos'!H16 -> 315000 | N8: ='Clientes e Ingresos'!H17 -> 340000 | O8: =SUM(C8:N8) -> 2780000
B9: Aporte de Capital Inicial / Socio | C9: =MAX(40000,(SUM($C$15:C15)-SUM($C$8:C8)),(SUM($C$15:D15)-SUM($C$8:D8)),(SUM($C$15:E15)-SUM($C$8:E8)),(SUM($C$15:F15)-SUM($C$8:F8)),(SUM($C$15:G15)-SUM($C$8:G8)),(SUM($C$15:H15)-SUM($C$8:H8)),(SUM($C$15:I15)-SUM($C$8:I8)),(SUM($C$15:J15)-SUM($C$8:J8)),(SUM($C$15:K15)-SUM($C$8:K8)),(SUM($C$15:L15)-SUM($C$8:L8)),(SUM($C$15:M15)-SUM($C$8:M8)),(SUM($C$15:N15)-SUM($C$8:N8))) -> 40000 | D9: 0 | E9: 0 | F9: 0 | G9: 0 | H9: 0 | I9: 0 | J9: 0 | K9: 0 | L9: 0 | M9: 0 | N9: 0 | O9: =SUM(C9:N9) -> 40000
B10: TOTAL ENTRADAS | C10: =SUM(C8:C9) -> 155000 | D10: =SUM(D8:D9) -> 140000 | E10: =SUM(E8:E9) -> 165000 | F10: =SUM(F8:F9) -> 190000 | G10: =SUM(G8:G9) -> 215000 | H10: =SUM(H8:H9) -> 215000 | I10: =SUM(I8:I9) -> 240000 | J10: =SUM(J8:J9) -> 265000 | ... N10: =SUM(N8:N9) -> 340000 | O10: =SUM(C10:N10) -> 2820000
B11: SALIDAS DE EFECTIVO
B12: Desarrollo: desembolso efectivo | C12: =0 -> 0 | D12: 0 | E12: 0 | F12: 0 | G12: 0 | H12: 0 | I12: 0 | J12: 0 | K12: 0 | L12: 0 | M12: 0 | N12: 0 | O12: =SUM(C12:N12) -> 0
B13: Gastos Fijos Operativos (OPEX) | C13: ='Egresos e Inversión'!D35-(4+36)*(496838.17/30/8) -> 109125 | D13: ='Egresos e Inversión'!D36-(4+12)*(496838.17/30/8) -> 81125 | E13: ='Egresos e Inversión'!D37-(4+12)*(496838.17/30/8) -> 81125 | F13: ='Egresos e Inversión'!D38-(4+12)*(496838.17/30/8) -> 81125 | G13: ='Egresos e Inversión'!D39-(4+12)*(496838.17/30/8) -> 81125 | H13: ='Egresos e Inversión'!D40-(4+12)*(496838.17/30/8) -> 81125 | I13: ='Egresos e Inversión'!D41-(4+12)*(496838.17/30/8) -> 81125 | J13: ='Egresos e Inversión'!D42-(4+12)*(496838.17/30/8) -> 81125 | K13: ='Egresos e Inversión'!D43-(4+12)*(496838.17/30/8) -> 81125 | L13: ='Egresos e Inversión'!D44-(4+12)*(496838.17/30/8) -> 81125 | M13: ='Egresos e Inversión'!D45-(4+12)*(496838.17/30/8) -> 81125 | N13: ='Egresos e Inversión'!D46-(4+12)*(496838.17/30/8) -> 81125 | O13: =SUM(C13:N13) -> 1001500
B14: Servicios y nube: pagos externos | C14: ='Egresos e Inversión'!E35-('Clientes e Ingresos'!F6*0.5+'Clientes e Ingresos'!D6*8)*(496838.17/30/8) -> 1982.79 | D14: ='Egresos e Inversión'!E36-('Clientes e Ingresos'!F7*0.5+'Clientes e Ingresos'!D7*8)*(496838.17/30/8) -> 2433.2 | E14: ='Egresos e Inversión'!E37-('Clientes e Ingresos'!F8*0.5+'Clientes e Ingresos'!D8*8)*(496838.17/30/8) -> 2883.61 | F14: ='Egresos e Inversión'!E38-('Clientes e Ingresos'!F9*0.5+'Clientes e Ingresos'!D9*8)*(496838.17/30/8) -> 13334.02 | G14: ='Egresos e Inversión'!E39-('Clientes e Ingresos'!F10*0.5+'Clientes e Ingresos'!D10*8)*(496838.17/30/8) -> 13784.43 | H14: ='Egresos e Inversión'!E40-('Clientes e Ingresos'!F11*0.5+'Clientes e Ingresos'!D11*8)*(496838.17/30/8) -> 13784.43 | I14: ='Egresos e Inversión'!E41-('Clientes e Ingresos'!F12*0.5+'Clientes e Ingresos'!D12*8)*(496838.17/30/8) -> 14234.84 | J14: ='Egresos e Inversión'!E42-('Clientes e Ingresos'!F13*0.5+'Clientes e Ingresos'!D13*8)*(496838.17/30/8) -> 17185.25 | K14: ='Egresos e Inversión'!E43-('Clientes e Ingresos'!F14*0.5+'Clientes e Ingresos'!D14*8)*(496838.17/30/8) -> 17635.66 | L14: ='Egresos e Inversión'!E44-('Clientes e Ingresos'!F15*0.5+'Clientes e Ingresos'!D15*8)*(496838.17/30/8) -> 17635.66 | M14: ='Egresos e Inversión'!E45-('Clientes e Ingresos'!F16*0.5+'Clientes e Ingresos'!D16*8)*(496838.17/30/8) -> 18086.07 | N14: ='Egresos e Inversión'!E46-('Clientes e Ingresos'!F17*0.5+'Clientes e Ingresos'!D17*8)*(496838.17/30/8) -> 18536.48 | O14: =SUM(C14:N14) -> 151516.44
B15: TOTAL SALIDAS | C15: =SUM(C12:C14) -> 111107.79 | D15: =SUM(D12:D14) -> 83558.2 | E15: =SUM(E12:E14) -> 84008.61 | F15: =SUM(F12:F14) -> 94459.02 | G15: =SUM(G12:G14) -> 94909.43 | H15: =SUM(H12:H14) -> 94909.43 | I15: =SUM(I12:I14) -> 95359.84 | J15: =SUM(J12:J14) -> 98310.25 | ... N15: =SUM(N12:N14) -> 99661.48 | O15: =SUM(C15:N15) -> 1153016.4
B16: FLUJO NETO DE CAJA MENSUAL | C16: =C10-C15 -> 43892.21 | D16: =D10-D15 -> 56441.8 | E16: =E10-E15 -> 80991.39 | F16: =F10-F15 -> 95540.98 | G16: =G10-G15 -> 120090.57 | H16: =H10-H15 -> 120090.57 | I16: =I10-I15 -> 144640.16 | J16: =J10-J15 -> 166689.75 | ... N16: =N10-N15 -> 240338.52 | O16: =SUM(C16:N16) -> 1666983.6
B17: SALDO DE CAJA ACUMULADO | C17: =C16 -> 43892.21 | D17: =C17+D16 -> 100334.01 | E17: =D17+E16 -> 181325.4 | F17: =E17+F16 -> 276866.38 | G17: =F17+G16 -> 396956.95 | H17: =G17+H16 -> 517047.52 | I17: =H17+I16 -> 661687.68 | J17: =I17+J16 -> 828377.43 | K17: =J17+K16 -> 1019616.8 | ... N17: =M17+N16 -> 1666983.6 | O17: =N17 -> 1666983.6
B20: 2. ESTADO DE GANANCIAS Y PÉRDIDAS PROYECTADO (AÑO 1)
B21: Estructura del Estado de Resultados | C21: Monto Anual (₡) | D21: % sobre Ventas
B22: Ingresos Operativos Totales (Ventas) | C22: ='Clientes e Ingresos'!H18 -> 2780000 | D22: 1
B23: (-) Costos Directos de Operación | C23: ='Egresos e Inversión'!E47 -> 536566.02 | D23: =C23/C22 -> 0.19300936
B24: UTILIDAD BRUTA | C24: =C22-C23 -> 2243434 | D24: =C24/C22 -> 0.80699064
B25: (-) Gastos Operativos Fijos | C25: ='Egresos e Inversión'!D47 -> 1448654.4 | D25: =C25/C22 -> 0.52109869
B26: RESULTADO ANTES DEL DESARROLLO | C26: =C24-C25 -> 794779.63 | D26: =C26/C22 -> 0.28589195
B27: (-) Desarrollo inicial (gasto del año) | C27: ='Egresos e Inversión'!D12 -> 198735.27 | D27: =C27/C22 -> 0.071487506
B28: UTILIDAD ANTES DE IMPUESTOS | C28: =C26-C27 -> 596044.36 | D28: =C28/C22 -> 0.21440445
B29: Renta: escenario MYPE formalizada | C29: =0 -> 0 | D29: =IFERROR(C29/C22,0) -> 0 | E29: 0% del impuesto determinado en años 1–3, condicionado a registros y requisitos. Pulso todavía sin registrar.
B30: RESULTADO ECONÓMICO · ESCENARIO MYPE | C30: =C28-C29 -> 596044.36 | D30: =C30/C22 -> 0.21440445
B32: 3. BALANCE ECONÓMICO (APORTES DE EFECTIVO Y TRABAJO)
B33: Cuenta Contable | C33: Monto al Cierre (₡) | E33: Cuenta Contable | F33: Monto al Cierre (₡)
B34: ACTIVOS CORRIENTES | E34: PASIVOS CORRIENTES
B35: Efectivo y Bancos (Caja Final) | C35: =N17 -> 1666983.6 | E35: Deuda financiera modelada | F35: =0 -> 0
B36: TOTAL ACTIVOS CORRIENTES | C36: =C35 -> 1666983.6 | E36: TOTAL PASIVOS CORRIENTES | F36: =F35 -> 0
B37: ACTIVOS NO CORRIENTES | E37: PATRIMONIO
B38: Desarrollo capitalizado (no aplicado) | C38: =0 -> 0 | E38: Aportes de efectivo y trabajo | F38: =C9+'Egresos e Inversión'!D12+'Egresos e Inversión'!D47+'Egresos e Inversión'!E47-O15 -> 1070939.2
B39: Amortización (no aplicada) | C39: =0 -> 0 | E39: Utilidades Acumuladas del Ejercicio | F39: =C30 -> 596044.36
B40: TOTAL ACTIVOS NO CORRIENTES | C40: =C38-C39 -> 0 | E40: TOTAL PATRIMONIO | F40: =F38+F39 -> 1666983.6
B41: TOTAL ACTIVOS | C41: =C36+C40 -> 1666983.6 | E41: TOTAL PASIVO + PATRIMONIO | F41: =F36+F40 -> 1666983.6
